addrparser/__init__.py
addrparser/cli.py
addrparser/locales/fi.py
addrparser/parser.py
addrparser/py.typed
addrparser-0.2.0.dist-info/entry_points.txt
addrparser-0.2.0.dist-info/LICENSE
addrparser-0.2.0.dist-info/WHEEL
addrparser-0.2.0.dist-info/METADATA
addrparser-0.2.0.dist-info/RECORD
