Metadata-Version: 2.1
Name: addrparser
Version: 0.2.0
Summary: Address parser for Finnish addresses
License: MIT
Author: Lauri Kajan
Author-email: lauri.kajan@gispo.fi
Requires-Python: >=3.6.2,<4.0.0
Classifier: Development Status :: 2 - Pre-Alpha
Classifier: Intended Audience :: Developers
Classifier: License :: OSI Approved :: MIT License
Classifier: Natural Language :: English
Classifier: Programming Language :: Python :: 3
Classifier: Programming Language :: Python :: 3.7
Classifier: Programming Language :: Python :: 3.8
Classifier: Programming Language :: Python :: 3.9
Classifier: Programming Language :: Python :: 3.10
Classifier: Programming Language :: Python :: 3
Classifier: Programming Language :: Python :: 3.6
Classifier: Programming Language :: Python :: 3.7
Classifier: Programming Language :: Python :: 3.8
Classifier: Programming Language :: Python :: 3.9
Provides-Extra: cli
Provides-Extra: dev
Provides-Extra: doc
Provides-Extra: test
Requires-Dist: black (>=22.3.0,<23.0.0); extra == "test"
Requires-Dist: bump2version (>=1.0.1,<2.0.0); extra == "dev"
Requires-Dist: click (==8.0.4); (python_version == "3.6") and (extra == "cli" or extra == "test")
Requires-Dist: click (>=8.1.3,<9.0.0); (python_full_version > "3.6.0") and (extra == "cli" or extra == "test")
Requires-Dist: flake8 (<4.0.0); extra == "test"
Requires-Dist: isort (>=5.10.1,<6.0.0); extra == "test"
Requires-Dist: jinja2 (>=3.1.2,<4.0.0); extra == "dev"
Requires-Dist: mkdocs (>=1.3.0,<2.0.0); extra == "doc"
Requires-Dist: mkdocs-autorefs (>=0.4.1,<0.5.0); extra == "doc"
Requires-Dist: mkdocs-include-markdown-plugin (>=3.5.2,<4.0.0); extra == "doc"
Requires-Dist: mkdocs-material (>=8.3.4,<9.0.0); extra == "doc"
Requires-Dist: mkdocstrings[python] (==0.17.0); (python_version == "3.6") and (extra == "doc")
Requires-Dist: mkdocstrings[python] (>=0.19.0,<0.20.0); (python_full_version > "3.6.0") and (extra == "doc")
Requires-Dist: mypy (>=0.961,<0.962); extra == "test"
Requires-Dist: pre-commit (>=2.19.0,<3.0.0); extra == "dev"
Requires-Dist: pymdown-extensions (>=9.5,<10.0); extra == "doc"
Requires-Dist: pyparsing (>=3.0.9,<4.0.0)
Requires-Dist: pytest (==7.0.1); (python_version == "3.6") and (extra == "test")
Requires-Dist: pytest (>=7.1.2,<8.0.0); (python_full_version > "3.6.0") and (extra == "test")
Requires-Dist: pytest-cov (>=3.0.0,<4.0.0); extra == "test"
Requires-Dist: railroad-diagrams (>=1.1.1,<2.0.0); extra == "dev"
Requires-Dist: tox (>=3.25.0,<4.0.0); extra == "dev"
